{"login":"Lily-F-Guerra","id":115589260,"node_id":"U_kgDOBuPAjA","avatar_url":"https://avatars.githubusercontent.com/u/115589260?v=4","gravatar_id":"","url":"https://api.github.com/users/Lily-F-Guerra","html_url":"https://github.com/Lily-F-Guerra","followers_url":"https://api.github.com/users/Lily-F-Guerra/followers","following_url":"https://api.github.com/users/Lily-F-Guerra/following{/other_user}","gists_url":"https://api.github.com/users/Lily-F-Guerra/gists{/gist_id}","starred_url":"https://api.github.com/users/Lily-F-Guerra/starred{/owner}{/repo}","subscriptions_url":"https://api.github.com/users/Lily-F-Guerra/subscriptions","organizations_url":"https://api.github.com/users/Lily-F-Guerra/orgs","repos_url":"https://api.github.com/users/Lily-F-Guerra/repos","events_url":"https://api.github.com/users/Lily-F-Guerra/events{/privacy}","received_events_url":"https://api.github.com/users/Lily-F-Guerra/received_events","type":"User","site_admin":false,"name":"Lily F Guerra","company":null,"blog":"","location":null,"email":null,"hireable":null,"bio":null,"twitter_username":null,"public_repos":1,"public_gists":0,"followers":0,"following":0,"created_at":"2022-10-11T20:24:02Z","updated_at":"2022-10-12T19:46:02Z","private_gists":0,"total_private_repos":0,"owned_private_repos":0,"disk_usage":3011,"collaborators":0,"two_factor_authentication":false,"plan":{"name":"free","space":976562499,"collaborators":0,"private_repos":10000}}